{"cameraMode":{"drawMode":0,"name":"Shaded","section":"Shading Mode"},"sceneLighting":true,"audioPlay":false,"sceneViewState":{"m_AlwaysRefresh":false,"showFog":true,"showSkybox":true,"showFlares":true,"showImageEffects":true,"showParticleSystems":true,"showVisualEffectGraphs":true,"m_FxEnabled":true},"in2DMode":false,"pivot":{"x":46.3464241027832,"y":9.069421768188477,"z":18.16583824157715},"rotation":{"x":0.04776992276310921,"y":0.8913305997848511,"z":-0.0966353490948677,"w":0.44049519300460818},"size":0.894871175289154,"orthographic":false}